{
    "neovim": {
        "branch": "master",
        "description": "Vim-fork focused on extensibility and usability",
        "homepage": "https://neovim.io",
        "owner": "neovim",
        "repo": "neovim",
        "rev": "45ba2e147f7b7d17acb489d64acc257ceded0887",
        "sha256": "1nn5lby53g5j5msb8xa9nndwrnh213a5bxiva2a9fzhbk4j1kbmp",
        "type": "tarball",
        "url": "https://github.com/neovim/neovim/archive/45ba2e147f7b7d17acb489d64acc257ceded0887.tar.gz",
        "url_template": "https://github.com/<owner>/<repo>/archive/<rev>.tar.gz"
    }
}
