{
  "version": "0.9.0-dev.952+0c091feb5",
  "date": "2021-09-10",
  "docs": "https://ziglang.org/documentation/master/",
  "stdDocs": "https://ziglang.org/documentation/master/std/",
  "src": {
    "tarball": "https://ziglang.org/builds/zig-0.9.0-dev.952+0c091feb5.tar.xz",
    "shasum": "084d0ca532f2883c3925863baf0c85cda3e16eeeef98d3646820a72dbd82d53f",
    "size": "12840252"
  },
  "x86_64-freebsd": {
    "tarball": "https://ziglang.org/builds/zig-freebsd-x86_64-0.9.0-dev.952+0c091feb5.tar.xz",
    "shasum": "a1335867abcc6c9160dfc4eb45eb70e1a4b9b4019ecddf1ea818ade5ca339dfd",
    "size": "41241688"
  },
  "x86_64-netbsd": {
    "tarball": "https://ziglang.org/builds/zig-netbsd-x86_64-0.9.0-dev.952+0c091feb5.tar.xz",
    "shasum": "53a9271704d8ba76efd9971681586d66c0d4384a38050eef61a454019ac21f29",
    "size": "38689980"
  },
  "x86_64-macos": {
    "tarball": "https://ziglang.org/builds/zig-macos-x86_64-0.9.0-dev.952+0c091feb5.tar.xz",
    "shasum": "efd532009c482767ba9b4f0cbd9bbab65a787ac59d908d78bcf8eba6f9fcf1dd",
    "size": "39676372"
  },
  "aarch64-macos": {
    "tarball": "https://ziglang.org/builds/zig-macos-aarch64-0.9.0-dev.952+0c091feb5.tar.xz",
    "shasum": "e0e60edde9077e5ca0a08d58c6db4cb04f2ce069e43c6a562bf398eb6ff12f96",
    "size": "37043596"
  },
  "x86_64-windows": {
    "tarball": "https://ziglang.org/builds/zig-windows-x86_64-0.9.0-dev.952+0c091feb5.zip",
    "shasum": "b033d3ddd0e960b549aea905181ee16ee8c90b3439177c1d0de1045193c7ec30",
    "size": "58753083"
  },
  "x86_64-linux": {
    "tarball": "https://ziglang.org/builds/zig-linux-x86_64-0.9.0-dev.952+0c091feb5.tar.xz",
    "shasum": "a7f08282a9dd8e5a3b48f3b3a303fe2e7044c54eaba023ed53a382e4c3529488",
    "size": "41637296"
  },
  "aarch64-linux": {
    "tarball": "https://ziglang.org/builds/zig-linux-aarch64-0.9.0-dev.952+0c091feb5.tar.xz",
    "shasum": "298f60820c11aa65c25239f3ae69197a2e4d5fd5aa731792e3d2c0d4766ec018",
    "size": "36375848"
  }
}
