{
  "version": "0.9.0-dev.1945+efdb94486",
  "date": "2021-12-11",
  "docs": "https://ziglang.org/documentation/master/",
  "stdDocs": "https://ziglang.org/documentation/master/std/",
  "src": {
    "tarball": "https://ziglang.org/builds/zig-0.9.0-dev.1945+efdb94486.tar.xz",
    "shasum": "27c41db396a4b9e27b7e01ca3d4d3f5131c200b3555c5d80433279200da4bd7d",
    "size": "14200892"
  },
  "x86_64-freebsd": {
    "tarball": "https://ziglang.org/builds/zig-freebsd-x86_64-0.9.0-dev.1945+efdb94486.tar.xz",
    "shasum": "375da24917612239f31ad6d3e9dec820a204a35436e868b4b80a029bb67ed8a9",
    "size": "43948636"
  },
  "x86_64-macos": {
    "tarball": "https://ziglang.org/builds/zig-macos-x86_64-0.9.0-dev.1945+efdb94486.tar.xz",
    "shasum": "1390537d399ce66071bf1fc660b7c77461c429b651f09f0b4ce1b5dd63064c9b",
    "size": "43138188"
  },
  "aarch64-macos": {
    "tarball": "https://ziglang.org/builds/zig-macos-aarch64-0.9.0-dev.1945+efdb94486.tar.xz",
    "shasum": "c4296ecf235e4df98f66ef3a7bb5fa589e40cb5cd18f8197df603a01d02d66a6",
    "size": "40701268"
  },
  "x86_64-windows": {
    "tarball": "https://ziglang.org/builds/zig-windows-x86_64-0.9.0-dev.1945+efdb94486.zip",
    "shasum": "472118bd75ebc904c6d57b75f706a45eb4bef1adb1e2faabfad77c6b8748192c",
    "size": "63674412"
  },
  "x86_64-linux": {
    "tarball": "https://ziglang.org/builds/zig-linux-x86_64-0.9.0-dev.1945+efdb94486.tar.xz",
    "shasum": "df0483a36fc8fd6dabe67c3b3269d1f5cdf674083206751f1dbf6db8449b0735",
    "size": "43939832"
  },
  "aarch64-linux": {
    "tarball": "https://ziglang.org/builds/zig-linux-aarch64-0.9.0-dev.1945+efdb94486.tar.xz",
    "shasum": "f8f5fc0fddc7b2d14fc57c950b0b7265ea708934cfbccd5a4a50d9b9438cb50f",
    "size": "40292384"
  }
}
