{
  "version": "0.9.0-dev.185+e125ead2b",
  "date": "2021-06-16",
  "docs": "https://ziglang.org/documentation/master/",
  "stdDocs": "https://ziglang.org/documentation/master/std/",
  "src": {
    "tarball": "https://ziglang.org/builds/zig-0.9.0-dev.185+e125ead2b.tar.xz",
    "shasum": "d04c0f17a14835f0878ca91658f375fc579912bdeb506b1f4f2803a1eebd17a9",
    "size": "13210356"
  },
  "x86_64-freebsd": {
    "tarball": "https://ziglang.org/builds/zig-freebsd-x86_64-0.9.0-dev.185+e125ead2b.tar.xz",
    "shasum": "aafaa1b710dc30ca58cebf30369777f2e2f84280b0ca7b85f95680ce0bc3098a",
    "size": "41492200"
  },
  "x86_64-macos": {
    "tarball": "https://ziglang.org/builds/zig-macos-x86_64-0.9.0-dev.185+e125ead2b.tar.xz",
    "shasum": "d1f72fcacfef3ef588e5a2631d64615b503ef13d771e54acf44a85c82be6cba9",
    "size": "39644744"
  },
  "aarch64-macos": {
    "tarball": "https://ziglang.org/builds/zig-macos-aarch64-0.9.0-dev.185+e125ead2b.tar.xz",
    "shasum": "39671e3fd9021d7f21c52a8a5fe797f8c9d48cca1eb3fc325765ee8e0a91815f",
    "size": "35531884"
  },
  "x86_64-windows": {
    "tarball": "https://ziglang.org/builds/zig-windows-x86_64-0.9.0-dev.185+e125ead2b.zip",
    "shasum": "1c78abb4a279ab7dcf67a94546344b006b7bce8c998c910bb3c2a1072085abde",
    "size": "59346138"
  },
  "x86_64-linux": {
    "tarball": "https://ziglang.org/builds/zig-linux-x86_64-0.9.0-dev.185+e125ead2b.tar.xz",
    "shasum": "e4693050ceaf976da3f8a2d2939e19e2dba6bf9aba1a1f97b4958c4a7d812e91",
    "size": "41925848"
  },
  "aarch64-linux": {
    "tarball": "https://ziglang.org/builds/zig-linux-aarch64-0.9.0-dev.185+e125ead2b.tar.xz",
    "shasum": "a213f2d8f7cfdd26cfe0fc8069428e9dc00aa5f6646f3447a98127df71e55076",
    "size": "36992260"
  }
}
